yolink/__init__.py
yolink/auth_mgr.py
yolink/client.py
yolink/client_request.py
yolink/const.py
yolink/device.py
yolink/device_helper.py
yolink/endpoint.py
yolink/exception.py
yolink/home_manager.py
yolink/local_auth_mgr.py
yolink/local_hub_client.py
yolink/message_listener.py
yolink/message_resolver.py
yolink/model.py
yolink/mqtt_client.py
yolink/outlet_request_builder.py
yolink/thermostat_request_builder.py
yolink/unit_helper.py
yolink_api-0.6.1.dist-info/licenses/LICENSE
yolink_api-0.6.1.dist-info/METADATA
yolink_api-0.6.1.dist-info/WHEEL
yolink_api-0.6.1.dist-info/top_level.txt
yolink_api-0.6.1.dist-info/RECORD
