Metadata-Version: 2.4
Name: yolink-api
Version: 0.6.1
Summary: A library to authenticate with yolink device
Author: YoSmart
License-Expression: MIT
Project-URL: Source, https://github.com/YoSmart-Inc/yolink-api
Project-URL: Bug Tracker, https://github.com/YoSmart-Inc/yolink-api/issues
Keywords: yolink,api
Classifier: Programming Language :: Python :: 3
Classifier: Operating System :: OS Independent
Requires-Python: >=3.9
License-File: LICENSE
Requires-Dist: aiohttp>=3.8.1
Requires-Dist: aiomqtt<3.0.0,>=2.0.0
Requires-Dist: pydantic>=2.0.0
Requires-Dist: tenacity>=8.1.0
Dynamic: license-file
